tsplib95/__init__.py
tsplib95/bisep.py
tsplib95/cli.py
tsplib95/distances.py
tsplib95/exceptions.py
tsplib95/fields.py
tsplib95/loaders.py
tsplib95/matrix.py
tsplib95/models.py
tsplib95/transformers.py
tsplib95/utils.py
tsplib95-0.7.1.dist-info/DESCRIPTION.rst
tsplib95-0.7.1.dist-info/METADATA
tsplib95-0.7.1.dist-info/RECORD
tsplib95-0.7.1.dist-info/WHEEL
tsplib95-0.7.1.dist-info/entry_points.txt
tsplib95-0.7.1.dist-info/metadata.json
tsplib95-0.7.1.dist-info/top_level.txt
tsplib95-0.7.1.dist-info/zip-safe
