Metadata-Version: 2.1
Name: tsplib95
Version: 0.7.1
Summary: TSPLIB95 works with TSPLIB95 files.
Home-page: https://github.com/rhgrant10/tsplib95
Author: Robert Grant
Author-email: rhgrant10@gmail.com
License: Apache Software License 2.0
Keywords: tsplib95
Platform: UNKNOWN
Classifier: Development Status :: 4 - Beta
Classifier: Intended Audience :: Developers
Classifier: Intended Audience :: Education
Classifier: Intended Audience :: Science/Research
Classifier: License :: OSI Approved :: Apache Software License
Classifier: Natural Language :: English
Classifier: Programming Language :: Python :: 3
Classifier: Programming Language :: Python :: 3.6
Classifier: Programming Language :: Python :: 3.7
Classifier: Programming Language :: Python :: 3 :: Only
Classifier: Operating System :: OS Independent
